hello.py
hello_ehmed-0.0.1.dist-info/DESCRIPTION.rst
hello_ehmed-0.0.1.dist-info/METADATA
hello_ehmed-0.0.1.dist-info/RECORD
hello_ehmed-0.0.1.dist-info/WHEEL
hello_ehmed-0.0.1.dist-info/entry_points.txt
hello_ehmed-0.0.1.dist-info/metadata.json
hello_ehmed-0.0.1.dist-info/top_level.txt
