Metadata-Version: 2.0
Name: hello-ehmed
Version: 0.0.1
Summary: describe please
Home-page: https://github.com/Ehmed-kino/wh_lilgarb.git
Author: Ehmed Kino
Author-email: ehmadaff@gmail.com
License: MIT
Platform: UNKNOWN
